causalmatch/__init__.py
causalmatch/matching/__init__.py
causalmatch/matching/_version.py
causalmatch/matching/match_core/TableFormat.py
causalmatch/matching/match_core/__init__.py
causalmatch/matching/match_core/ate.py
causalmatch/matching/match_core/cem.py
causalmatch/matching/match_core/meta_learner.py
causalmatch/matching/match_core/model.py
causalmatch/matching/match_core/mrd.py
causalmatch/matching/match_core/preprocess.py
causalmatch/matching/match_core/psm.py
causalmatch/matching/match_core/robust_check.py
causalmatch/matching/match_core/utils.py
causalmatch/matching/match_core/utils_mrd.py
causalmatch/tests/__init__.py
causalmatch/tests/unittest_ate.py
causalmatch-0.0.6.dist-info/licenses/LICENSE.txt
notebooks/__init__.py
causalmatch-0.0.6.dist-info/METADATA
causalmatch-0.0.6.dist-info/WHEEL
causalmatch-0.0.6.dist-info/top_level.txt
causalmatch-0.0.6.dist-info/RECORD
