Metadata-Version: 2.4
Name: causalmatch
Version: 0.0.6
Summary: Propensity score matching and coarsened exact matching
Home-page: https://github.com/bytedance/CausalMatch
Author: Xiaoyu Zhou
Author-email: xiaoyuzhou@bytedance.com
Requires-Python: >=3.6
License-File: LICENSE.txt
Requires-Dist: pandas<=1.3.5,>=1.3.4
Requires-Dist: numpy<=1.26.4,>=1.3.0
Requires-Dist: scikit-learn>=1.4.0
Requires-Dist: tqdm>=4.66.2
Requires-Dist: statsmodels>=0.14.1
Requires-Dist: lightgbm>=4.3.0
Requires-Dist: xgboost>=2.0.3
Requires-Dist: matplotlib>=3.8.3
Requires-Dist: FixedEffectModel>=0.0.5
Dynamic: author
Dynamic: author-email
Dynamic: home-page
Dynamic: license-file
Dynamic: requires-dist
Dynamic: requires-python
Dynamic: summary
